mistelaflask/__init__.py
mistelaflask/auth.py
mistelaflask/models.py
mistelaflask/templates/admin/admin.html
mistelaflask/templates/admin/admin_index.html
mistelaflask/templates/admin/admin_navbar.html
mistelaflask/templates/admin/events/admin_event_form.html
mistelaflask/templates/admin/events/admin_events_add.html
mistelaflask/templates/admin/events/admin_events_base.html
mistelaflask/templates/admin/events/admin_events_detail.html
mistelaflask/templates/admin/events/admin_events_list.html
mistelaflask/templates/admin/guests/admin_guest_form.html
mistelaflask/templates/admin/guests/admin_guests_add.html
mistelaflask/templates/admin/guests/admin_guests_add_batch.html
mistelaflask/templates/admin/guests/admin_guests_base.html
mistelaflask/templates/admin/guests/admin_guests_detail.html
mistelaflask/templates/admin/guests/admin_guests_list.html
mistelaflask/templates/admin/invitations/admin_invitation_edit_bulk.html
mistelaflask/templates/admin/invitations/admin_invitation_form.html
mistelaflask/templates/admin/invitations/admin_invitations_add.html
mistelaflask/templates/admin/invitations/admin_invitations_base.html
mistelaflask/templates/admin/invitations/admin_invitations_detail.html
mistelaflask/templates/admin/invitations/admin_invitations_list.html
mistelaflask/templates/admin/invitations/admin_invitations_summary.html
mistelaflask/templates/admin/locations/admin_location_form.html
mistelaflask/templates/admin/locations/admin_locations_add.html
mistelaflask/templates/admin/locations/admin_locations_base.html
mistelaflask/templates/admin/locations/admin_locations_detail.html
mistelaflask/templates/admin/locations/admin_locations_list.html
mistelaflask/templates/admin/main_events/admin_main_event_form.html
mistelaflask/templates/admin/main_events/admin_main_events_add.html
mistelaflask/templates/admin/main_events/admin_main_events_base.html
mistelaflask/templates/admin/main_events/admin_main_events_detail.html
mistela_flask-0.16.1.dist-info/entry_points.txt
mistela_flask-0.16.1.dist-info/LICENSE
mistela_flask-0.16.1.dist-info/WHEEL
mistela_flask-0.16.1.dist-info/METADATA
mistela_flask-0.16.1.dist-info/RECORD
