Metadata-Version: 2.1
Name: mistela-flask
Version: 0.16.1
Summary: A multi-event planner flask application. It allows for RSVP options, authentication, and guest management
Home-page: https://github.com/carsopre/mistela-flask
License: MIT
Author: Carles S. Soriano Perez
Author-email: sorianoperez.carles@gmail.com
Requires-Python: >=3.9,<4.0
Classifier: Development Status :: 2 - Pre-Alpha
Classifier: Framework :: Flask
Classifier: Intended Audience :: Developers
Classifier: Intended Audience :: Education
Classifier: License :: OSI Approved :: MIT License
Classifier: Natural Language :: English
Classifier: Programming Language :: Python :: 3
Classifier: Programming Language :: Python :: 3.10
Classifier: Programming Language :: Python :: 3.9
Classifier: Topic :: Internet :: WWW/HTTP :: WSGI :: Application
Classifier: Topic :: Software Development :: Libraries :: Python Modules
Requires-Dist: Flask (>=2.2.2,<3.0.0)
Requires-Dist: Flask-Login (>=0.6.2,<0.7.0)
Requires-Dist: Flask-Mail (>=0.9.1,<0.10.0)
Requires-Dist: commitizen (>=2.35.0,<3.0.0)
Requires-Dist: flask-sqlalchemy (>=3.0.2,<4.0.0)
Requires-Dist: gunicorn (>=20.1.0,<21.0.0)
Requires-Dist: pyOpenSSL (>=22.1.0,<23.0.0)
Project-URL: Repository, https://github.com/carsopre/mistela-flask
